pytter/__init__.py
pytter/users.py
Pytter2-0.0.1.dist-info/LICENSE
Pytter2-0.0.1.dist-info/METADATA
Pytter2-0.0.1.dist-info/WHEEL
Pytter2-0.0.1.dist-info/top_level.txt
Pytter2-0.0.1.dist-info/RECORD
