Metadata-Version: 2.1
Name: Pytter2
Version: 0.0.1
Summary: Read write Twitter data with API v2
Home-page: https://github.com/mlabarrere/Pytter2
Author: M_Lbr
Author-email: m.micky.lbr@gmail.com
License: UNKNOWN
Platform: UNKNOWN
Classifier: Programming Language :: Python :: 3
Classifier: License :: OSI Approved :: Apache Software License
Classifier: Operating System :: OS Independent
Classifier: Natural Language :: English
Requires-Dist: pygquery
